nightwalker/__init__.py
nightwalker-1.0.1.dist-info/LICENSE
nightwalker-1.0.1.dist-info/METADATA
nightwalker-1.0.1.dist-info/WHEEL
nightwalker-1.0.1.dist-info/top_level.txt
nightwalker-1.0.1.dist-info/RECORD
