Metadata-Version: 2.1
Name: nightwalker
Version: 1.0.1
Summary: Neural Network Supervision Platform
Home-page: https://github.com/deepconsc/NightCrawler
Author: SYSTEM CORP.
Author-email: contact@systemcorp.ai
License: MIT
Platform: UNKNOWN
Classifier: Development Status :: 3 - Alpha
Classifier: License :: OSI Approved :: MIT License
Classifier: Programming Language :: Python :: 3.6
Classifier: Programming Language :: Python :: 3.7
Classifier: Programming Language :: Python :: 3.8
Classifier: Topic :: Scientific/Engineering :: Artificial Intelligence
Classifier: Operating System :: OS Independent
Requires-Python: >=3.6
Requires-Dist: requests
